Workbook

Sheet 源清单
B2: ai-auto-gen 信息源清单（注册表全量 107 源，2026-08-31 导出）
B4: 序号 | C4: 源 id | D4: 市场 | E4: 类型 | F4: 给什么内容 | G4: 更新作息 | H4: 状态 | I4: 备注/坑
B5: 1 | C5: sina_7x24 | D5: A股/中国 | E5: 快讯流 | F5: 新浪财经7×24 | G5: 7×24 滚动 | H5: 启用
B6: 2 | C6: eastmoney_fast | D6: A股/中国 | E6: 快讯流 | F6: 东财财经快讯 | G6: 7×24 秒级 | H6: 启用 | I6: 焦点栏目
B7: 3 | C7: jin10_flash | D7: 全球/多市场 | E7: 快讯流 | F7: 金十数据快讯(全球,秒级时间戳) | G7: 7×24 秒级 | H7: 启用 | I7: 全球宏观
B8: 4 | C8: fxstreet_flash | D8: 全球/多市场 | E8: 快讯流 | F8: FXStreet外汇央行快讯(英文, 2026-08-30起出口IP被Cloudflare整站403, 待恢复) | G8: 交易日滚动 | H8: 占位·被拦待恢复 | I8: 出口 IP 被 Cloudflare 整站 403
B9: 5 | C9: investinglive_flash | D9: 全球/多市场 | E9: 快讯流 | F9: investingLive外汇/美股/宏观快讯(英文, 原ForexLive, FXStreet同赛道顶替) | G9: 交易日滚动 | H9: 启用 | I9: 英文, FXStreet 同赛道顶替
B10: 6 | C10: eastmoney_zaozhidao | D10: A股/中国 | E10: 同行文章 | F10: 东财搜索《早知道》系列 | G10: 每早 | H10: 启用 | I10: 《早知道》系列
B11: 7 | C11: wscn_breakfast | D11: 全球/多市场 | E11: 同行文章 | F11: 华尔街见闻早餐 | G11: 每早 | H11: 启用 | I11: 华尔街见闻早餐
B12: 8 | C12: futu_morning | D12: 港股 | E12: 同行文章 | F12: 富途《港美早报》 | G12: 工作日晨 | H12: 聚合 | I12: 富途《港美早报》
B13: 9 | C13: cls_morning | D13: A股/中国 | E13: 同行文章 | F13: 财联社有声早报(专栏1151, 每日07:00) | G13: 每日07:00 | H13: 聚合 | I13: 有声早报
B14: 10 | C14: aa_morning | D14: 土耳其 | E14: 同行文章 | F14: AA安纳多卢通讯社英文晨报 | G14: 每日晨 | H14: 聚合 | I14: AA 通讯社英文晨报
B15: 11 | C15: turkey_morning | D15: 土耳其 | E15: 同行文章 | F15: BloombergHT土耳其市场 | G15: 交易日晨 | H15: 聚合 | I15: BloombergHT
B16: 12 | C16: cnbc_morning | D16: 美股 | E16: 同行文章 | F16: CNBC Daily Open美股晨报(工作日) | G16: 工作日晨 | H16: 聚合 | I16: CNBC Daily Open
B17: 13 | C17: japan_morning | D17: 日本 | E17: 同行文章 | F17: 共同社日本市场精选(当日RSS过滤) | G17: 日内 RSS 过滤当日 | H17: 聚合 | I17: 共同社
... B80: 76 | C80: treasury_press | D80: 美股 | E80: 公告/披露 | F80: 美国财政部新闻稿RSS(仅/rss.xml有效路径) | G80: 发布即更 | H80: 启用 | I80: 仅 /rss.xml 有效路径
B81: 77 | C81: foxbusiness_rss | D81: 美股 | E81: 快讯流 | F81: Fox Business最新新闻流(英文零key) | G81: 分钟级 | H81: 启用
B82: 78 | C82: benzinga_rss | D82: 美股 | E82: 快讯流 | F82: Benzinga美股个股快讯+分析流(英文; 夹杂加密/预测类内容下游粗筛) | G82: 分钟级 | H82: 启用 | I82: 夹加密/预测软文, 下游粗筛
B83: 79 | C83: eia_energy | D83: 美股 | E83: 同行文章 | F83: EIA美国能源署Today in Energy(能源大宗基本面日报, 工作日每日) | G83: 工作日每日 | H83: 启用 | I83: 能源大宗基本面日报
B84: 80 | C84: finviz_news | D84: 美股 | E84: 快讯流 | F84: Finviz全市场新闻聚合(Bloomberg/Reuters/WSJ/CNBC等, 纯SSR零key带来源链接) | G84: 秒~分钟 | H84: 启用 | I84: 聚合 Bloomberg/Reuters/WSJ/CNBC 等
B85: 81 | C85: nyfed_rates | D85: 美股 | E85: 数据/宏观 | F85: 纽约联储SOFR/EFFR/OBFR/TGCR官方利率最新值(Markets API零key) | G85: 交易日日更 | H85: 启用 | I85: SOFR/EFFR/OBFR/TGCR 官方
B86: 82 | C86: bls_macro | D86: 美股 | E86: 数据/宏观 | F86: BLS美国CPI/非农/失业率最新值(公共API v1零key日限25次) | G86: 月度发布日 | H86: 启用 | I86: CPI/非农/失业率; v1 零 key 日限 25 次
B87: 83 | C87: fiscal_debt | D87: 美股 | E87: 数据/宏观 | F87: 美国财政部国债总额日更(Fiscal Data零key免注册, T+1) | G87: 工作日 T+1 | H87: 启用 | I87: 国债总额
B88: 84 | C88: globenewswire | D88: 美股 | E88: 公告/披露 | F88: 备用|GlobeNewswire上市公司稿流(2026-08-31本机出口IP多次ReadTimeout, 疑IDC段限制待复测) | G88: 分钟级 | H88: 占位·被拦待恢复 | I88: 本机出口 IP ReadTimeout, 疑 IDC 段限制
B89: 85 | C89: hkexnews | D89: 港股 | E89: 公告/披露 | F89: 港交所披露易公告检索API(上市公司法定披露一手源, 零key含代码+PDF直链) | G89: 实时随发随更 | H89: 启用 | I89: 披露易法定披露一手源, 代码+PDF 直链
B90: 86 | C90: mingpao_rss | D90: 港股 | E90: 快讯流 | F90: 明报即时财经RSS(港股IPO/中报/本地宏观, 盘中高频零key) | G90: 盘中高频 | H90: 启用 | I90: IPO 聆讯/中报/本地宏观
B91: 87 | C91: yahoo_hk_rss | D91: 港股 | E91: 快讯流 | F91: Yahoo香港财经新闻流(AASTOCKS AAFN快讯内容, 繁体带代码零key) | G91: 分钟级 | H91: 启用 | I91: AASTOCKS AAFN 内容, 繁体带代码
B92: 88 | C92: scmp_biz_rss | D92: 港股 | E92: 快讯流 | F92: SCMP南华早报Business频道(英文港股/中国财经视角, 标题摘要免费) | G92: 日内滚动 | H92: 启用 | I92: 英文; 标题摘要免费, 正文软付费墙
B93: 89 | C93: eastmoney_hkus | D93: 港股 | E93: 快讯流 | F93: 东财7×24快讯港美股频道(fastColumn=104, 与焦点102不同栏目) | G93: 7×24 秒级 | H93: 启用 | I93: fastColumn=104 港美股频道
... B111: 107 | C111: hkgov_finance | D111: 港股 | E111: 公告/披露 | F111: 备用|香港政府新闻网财经RSS(2026-08-31本机出口TLS被重置, 待部署环境复测) | G111: 不定期 | H111: 占位·被拦待恢复 | I111: 本机出口 TLS 被重置, 待部署环境复测

Sheet 总览
B2: 总览：按市场与状态统计（活公式，随源清单联动）
B4: 市场 | C4: 总数 | D4: 启用 | E4: 占位·被拦待恢复 | F4: 占位·待配key | G4: 聚合/手动
B5: A股/中国 | C5: =COUNTIF('源清单'!$D$5:$D$111,B5) | D5: =COUNTIFS('源清单'!$D$5:$D$111,B5,'源清单'!$H$5:$H$111,"启用") | E5: =COUNTIFS('源清单'!$D$5:$D$111,B5,'源清单'!$H$5:$H$111,"占位·被拦待恢复") | F5: =COUNTIFS('源清单'!$D$5:$D$111,B5,'源清单'!$H$5:$H$111,"占位·待配key") | G5: =COUNTIFS('源清单'!$D$5:$D$111,B5,'源清单'!$H$5:$H$111,"聚合")+COUNTIFS('源清单'!$D$5:$D$111,B5,'源清单'!$H$5:$H$111,"组合·手动")+COUNTIFS('源清单'!$D$5:$D$111,B5,'源清单'!$H$5:$H$111,"素材·手动")+COUNTIFS('源清单'!$D$5:$D$111,B5,'源清单'!$H$5:$H$111,"手动")
B6: 全球/多市场 | C6: =COUNTIF('源清单'!$D$5:$D$111,B6) | D6: =COUNTIFS('源清单'!$D$5:$D$111,B6,'源清单'!$H$5:$H$111,"启用") | E6: =COUNTIFS('源清单'!$D$5:$D$111,B6,'源清单'!$H$5:$H$111,"占位·被拦待恢复") | F6: =COUNTIFS('源清单'!$D$5:$D$111,B6,'源清单'!$H$5:$H$111,"占位·待配key") | G6: =COUNTIFS('源清单'!$D$5:$D$111,B6,'源清单'!$H$5:$H$111,"聚合")+COUNTIFS('源清单'!$D$5:$D$111,B6,'源清单'!$H$5:$H$111,"组合·手动")+COUNTIFS('源清单'!$D$5:$D$111,B6,'源清单'!$H$5:$H$111,"素材·手动")+COUNTIFS('源清单'!$D$5:$D$111,B6,'源清单'!$H$5:$H$111,"手动")
B7: 美股 | C7: =COUNTIF('源清单'!$D$5:$D$111,B7) | D7: =COUNTIFS('源清单'!$D$5:$D$111,B7,'源清单'!$H$5:$H$111,"启用") | E7: =COUNTIFS('源清单'!$D$5:$D$111,B7,'源清单'!$H$5:$H$111,"占位·被拦待恢复") | F7: =COUNTIFS('源清单'!$D$5:$D$111,B7,'源清单'!$H$5:$H$111,"占位·待配key") | G7: =COUNTIFS('源清单'!$D$5:$D$111,B7,'源清单'!$H$5:$H$111,"聚合")+COUNTIFS('源清单'!$D$5:$D$111,B7,'源清单'!$H$5:$H$111,"组合·手动")+COUNTIFS('源清单'!$D$5:$D$111,B7,'源清单'!$H$5:$H$111,"素材·手动")+COUNTIFS('源清单'!$D$5:$D$111,B7,'源清单'!$H$5:$H$111,"手动")
B8: 港股 | C8: =COUNTIF('源清单'!$D$5:$D$111,B8) | D8: =COUNTIFS('源清单'!$D$5:$D$111,B8,'源清单'!$H$5:$H$111,"启用") | E8: =COUNTIFS('源清单'!$D$5:$D$111,B8,'源清单'!$H$5:$H$111,"占位·被拦待恢复") | F8: =COUNTIFS('源清单'!$D$5:$D$111,B8,'源清单'!$H$5:$H$111,"占位·待配key") | G8: =COUNTIFS('源清单'!$D$5:$D$111,B8,'源清单'!$H$5:$H$111,"聚合")+COUNTIFS('源清单'!$D$5:$D$111,B8,'源清单'!$H$5:$H$111,"组合·手动")+COUNTIFS('源清单'!$D$5:$D$111,B8,'源清单'!$H$5:$H$111,"素材·手动")+COUNTIFS('源清单'!$D$5:$D$111,B8,'源清单'!$H$5:$H$111,"手动")
B9: 台湾 | C9: =COUNTIF('源清单'!$D$5:$D$111,B9) | D9: =COUNTIFS('源清单'!$D$5:$D$111,B9,'源清单'!$H$5:$H$111,"启用") | E9: =COUNTIFS('源清单'!$D$5:$D$111,B9,'源清单'!$H$5:$H$111,"占位·被拦待恢复") | F9: =COUNTIFS('源清单'!$D$5:$D$111,B9,'源清单'!$H$5:$H$111,"占位·待配key") | G9: =COUNTIFS('源清单'!$D$5:$D$111,B9,'源清单'!$H$5:$H$111,"聚合")+COUNTIFS('源清单'!$D$5:$D$111,B9,'源清单'!$H$5:$H$111,"组合·手动")+COUNTIFS('源清单'!$D$5:$D$111,B9,'源清单'!$H$5:$H$111,"素材·手动")+COUNTIFS('源清单'!$D$5:$D$111,B9,'源清单'!$H$5:$H$111,"手动")
B10: 土耳其 | C10: =COUNTIF('源清单'!$D$5:$D$111,B10) | D10: =COUNTIFS('源清单'!$D$5:$D$111,B10,'源清单'!$H$5:$H$111,"启用") | E10: =COUNTIFS('源清单'!$D$5:$D$111,B10,'源清单'!$H$5:$H$111,"占位·被拦待恢复") | F10: =COUNTIFS('源清单'!$D$5:$D$111,B10,'源清单'!$H$5:$H$111,"占位·待配key") | G10: =COUNTIFS('源清单'!$D$5:$D$111,B10,'源清单'!$H$5:$H$111,"聚合")+COUNTIFS('源清单'!$D$5:$D$111,B10,'源清单'!$H$5:$H$111,"组合·手动")+COUNTIFS('源清单'!$D$5:$D$111,B10,'源清单'!$H$5:$H$111,"素材·手动")+COUNTIFS('源清单'!$D$5:$D$111,B10,'源清单'!$H$5:$H$111,"手动")
B11: 日本 | C11: =COUNTIF('源清单'!$D$5:$D$111,B11) | D11: =COUNTIFS('源清单'!$D$5:$D$111,B11,'源清单'!$H$5:$H$111,"启用") | E11: =COUNTIFS('源清单'!$D$5:$D$111,B11,'源清单'!$H$5:$H$111,"占位·被拦待恢复") | F11: =COUNTIFS('源清单'!$D$5:$D$111,B11,'源清单'!$H$5:$H$111,"占位·待配key") | G11: =COUNTIFS('源清单'!$D$5:$D$111,B11,'源清单'!$H$5:$H$111,"聚合")+COUNTIFS('源清单'!$D$5:$D$111,B11,'源清单'!$H$5:$H$111,"组合·手动")+COUNTIFS('源清单'!$D$5:$D$111,B11,'源清单'!$H$5:$H$111,"素材·手动")+COUNTIFS('源清单'!$D$5:$D$111,B11,'源清单'!$H$5:$H$111,"手动")
B12: 韩国 | C12: =COUNTIF('源清单'!$D$5:$D$111,B12) | D12: =COUNTIFS('源清单'!$D$5:$D$111,B12,'源清单'!$H$5:$H$111,"启用") | E12: =COUNTIFS('源清单'!$D$5:$D$111,B12,'源清单'!$H$5:$H$111,"占位·被拦待恢复") | F12: =COUNTIFS('源清单'!$D$5:$D$111,B12,'源清单'!$H$5:$H$111,"占位·待配key") | G12: =COUNTIFS('源清单'!$D$5:$D$111,B12,'源清单'!$H$5:$H$111,"聚合")+COUNTIFS('源清单'!$D$5:$D$111,B12,'源清单'!$H$5:$H$111,"组合·手动")+COUNTIFS('源清单'!$D$5:$D$111,B12,'源清单'!$H$5:$H$111,"素材·手动")+COUNTIFS('源清单'!$D$5:$D$111,B12,'源清单'!$H$5:$H$111,"手动")
B13: 合计 | C13: =SUM(C5:C12) | D13: =SUM(D5:D12) | E13: =SUM(E5:E12) | F13: =SUM(F5:F12) | G13: =SUM(G5:G12)
B16: 按类型
B17: 类型 | C17: 数量
B18: 快讯流 | C18: =COUNTIF('源清单'!$E$5:$E$111,B18)
B19: 公告/披露 | C19: =COUNTIF('源清单'!$E$5:$E$111,B19)
B20: 数据/宏观 | C20: =COUNTIF('源清单'!$E$5:$E$111,B20)
B21: 同行文章 | C21: =COUNTIF('源清单'!$E$5:$E$111,B21)
B22: 日历 | C22: =COUNTIF('源清单'!$E$5:$E$111,B22)
B23: 聚合组 | C23: =COUNTIF('源清单'!$E$5:$E$111,B23)
B24: 素材组 | C24: =COUNTIF('源清单'!$E$5:$E$111,B24)
B27: 口径：sources/base.py REGISTRY 实时导出（python cli.py sources list 同源），作息/备注为人工维护映射。
B28: 状态释义：启用=默认进采集池；聚合=经 peer_mornings 同行早报聚合采集（单行默认关）；占位=代码在册默认关，被拦待恢复或待配免费 key。
B29: 法定披露层五市场齐备：A股巨潮 / 港股披露易 / 美股 EDGAR / 台湾 TWSE+TPEx 重大讯息 / 土耳其 KAP。
B30: 生成时选取：flows run --set flash_sources=... 或 config.yaml 的 sources.<id>.enabled。
